[{"county_name":"Lafourche","description":null,"feat_class":"Populated Place","feature_id":"11269","fips_class":"C1","fips_county_cd":"57","full_county_name":"Lafourche Parish","link_title":null,"url":"http:\/\/www.townofgoldenmeadow.com\/","name":"Golden Meadow","primary_latitude":"29.37","primary_longitude":"-90.26","state_abbreviation":"LA","state_name":"Louisiana"},{"county_name":"Ascension","description":null,"feat_class":"Populated Place","feature_id":"11271","fips_class":"C1","fips_county_cd":"5","full_county_name":"Ascension Parish","link_title":null,"url":"http:\/\/gonzalesla.com\/","name":"Gonzales","primary_latitude":"30.23","primary_longitude":"-90.92","state_abbreviation":"LA","state_name":"Louisiana"},{"county_name":"Jefferson","description":null,"feat_class":"Populated Place","feature_id":"11280","fips_class":"C1","fips_county_cd":"51","full_county_name":"Jefferson Parish","link_title":null,"url":"http:\/\/www.gretnala.com\/","name":"Gretna","primary_latitude":"29.91","primary_longitude":"-90.05","state_abbreviation":"LA","state_name":"Louisiana"},{"county_name":"Tangipahoa","description":null,"feat_class":"Populated Place","feature_id":"11284","fips_class":"C1","fips_county_cd":"105","full_county_name":"Tangipahoa Parish","link_title":null,"url":"http:\/\/www.hammond.org\/","name":"Hammond","primary_latitude":"30.5","primary_longitude":"-90.46","state_abbreviation":"LA","state_name":"Louisiana"},{"county_name":"Vernon","description":null,"feat_class":"Populated Place","feature_id":"11294","fips_class":"C1","fips_county_cd":"115","full_county_name":"Vernon Parish","link_title":null,"url":"http:\/\/townofhornbeck.com\/","name":"Hornbeck","primary_latitude":"31.32","primary_longitude":"-93.39","state_abbreviation":"LA","state_name":"Louisiana"},{"county_name":"Terrebonne","description":null,"feat_class":"Populated Place","feature_id":"11296","fips_class":"C9","fips_county_cd":"109","full_county_name":"Terrebonne Parish","link_title":null,"url":"http:\/\/www.tpcg.org\/","name":"Houma","primary_latitude":"29.5957696","primary_longitude":"-90.7195348","state_abbreviation":"LA","state_name":"Louisiana"},{"county_name":"Jefferson Davis","description":null,"feat_class":"Populated Place","feature_id":"11306","fips_class":"C1","fips_county_cd":"53","full_county_name":"Jefferson Davis Parish","link_title":null,"url":"http:\/\/www.cityofjennings.com\/","name":"Jennings","primary_latitude":"30.22","primary_longitude":"-92.65","state_abbreviation":"LA","state_name":"Louisiana"},{"county_name":"Jackson","description":null,"feat_class":"Populated Place","feature_id":"11307","fips_class":"C1","fips_county_cd":"49","full_county_name":"Jackson Parish","link_title":null,"url":"http:\/\/www.townofjonesboro.org\/","name":"Jonesboro","primary_latitude":"32.24","primary_longitude":"-92.71","state_abbreviation":"LA","state_name":"Louisiana"},{"county_name":"Jefferson","description":null,"feat_class":"Populated Place","feature_id":"11313","fips_class":"C1","fips_county_cd":"51","full_county_name":"Jefferson Parish","link_title":null,"url":"http:\/\/www.kenner.la.us\/","name":"Kenner","primary_latitude":"29.99","primary_longitude":"-90.24","state_abbreviation":"LA","state_name":"Louisiana"},{"county_name":"Lafayette","description":null,"feat_class":"Populated Place","feature_id":"11320","fips_class":"C1","fips_county_cd":"55","full_county_name":"Lafayette Parish","link_title":null,"url":"http:\/\/www.lafayettela.gov\/","name":"Lafayette","primary_latitude":"30.22","primary_longitude":"-92.01","state_abbreviation":"LA","state_name":"Louisiana"},{"county_name":"Calcasieu","description":null,"feat_class":"Populated Place","feature_id":"11322","fips_class":"C1","fips_county_cd":"19","full_county_name":"Calcasieu Parish","link_title":null,"url":"http:\/\/www.cityoflakecharles.com\/","name":"Lake Charles","primary_latitude":"30.22","primary_longitude":"-93.21","state_abbreviation":"LA","state_name":"Louisiana"},{"county_name":"Livingston","description":null,"feat_class":"Populated Place","feature_id":"11329","fips_class":"C1","fips_county_cd":"63","full_county_name":"Livingston Parish","link_title":null,"url":"http:\/\/www.townoflivingston.com\/","name":"Livingston","primary_latitude":"30.5","primary_longitude":"-90.74","state_abbreviation":"LA","state_name":"Louisiana"},{"county_name":"Lafourche","description":null,"feat_class":"Populated Place","feature_id":"11331","fips_class":"C1","fips_county_cd":"57","full_county_name":"Lafourche Parish","link_title":null,"url":"http:\/\/www.townoflockport.com\/","name":"Lockport","primary_latitude":"29.64","primary_longitude":"-90.53","state_abbreviation":"LA","state_name":"Louisiana"},{"county_name":"Iberia","description":null,"feat_class":"Populated Place","feature_id":"11334","fips_class":"C1","fips_county_cd":"45","full_county_name":"Iberia Parish","link_title":null,"url":"http:\/\/www.loreauville.us\/","name":"Loreauville","primary_latitude":"30.05","primary_longitude":"-91.73","state_abbreviation":"LA","state_name":"Louisiana"},{"county_name":"St. Tammany","description":null,"feat_class":"Populated Place","feature_id":"11339","fips_class":"C1","fips_county_cd":"103","full_county_name":"St. Tammany Parish","link_title":null,"url":"http:\/\/www.cityofmandeville.com\/","name":"Mandeville","primary_latitude":"30.35","primary_longitude":"-90.06","state_abbreviation":"LA","state_name":"Louisiana"},{"county_name":"Webster","description":null,"feat_class":"Populated Place","feature_id":"11354","fips_class":"C1","fips_county_cd":"119","full_county_name":"Webster Parish","link_title":null,"url":"http:\/\/www.mindenusa.com\/","name":"Minden","primary_latitude":"32.61","primary_longitude":"-93.28","state_abbreviation":"LA","state_name":"Louisiana"},{"county_name":"Ouachita","description":null,"feat_class":"Populated Place","feature_id":"11355","fips_class":"C1","fips_county_cd":"73","full_county_name":"Ouachita Parish","link_title":null,"url":"http:\/\/www.ci.monroe.la.us\/","name":"Monroe","primary_latitude":"32.5","primary_longitude":"-92.11","state_abbreviation":"LA","state_name":"Louisiana"},{"county_name":"St. Mary","description":null,"feat_class":"Populated Place","feature_id":"11360","fips_class":"C1","fips_county_cd":"101","full_county_name":"St. Mary Parish","link_title":null,"url":"http:\/\/www.cityofmc.com\/","name":"Morgan City","primary_latitude":"29.69","primary_longitude":"-91.2","state_abbreviation":"LA","state_name":"Louisiana"},{"county_name":"Natchitoches","description":null,"feat_class":"Populated Place","feature_id":"11367","fips_class":"C1","fips_county_cd":"69","full_county_name":"Natchitoches Parish","link_title":null,"url":"http:\/\/www.natchitochesla.gov\/","name":"Natchitoches","primary_latitude":"31.76","primary_longitude":"-93.08","state_abbreviation":"LA","state_name":"Louisiana"},{"county_name":"Iberia","description":null,"feat_class":"Populated Place","feature_id":"11368","fips_class":"C1","fips_county_cd":"45","full_county_name":"Iberia Parish","link_title":null,"url":"http:\/\/www.cityofnewiberia.com\/","name":"New Iberia","primary_latitude":"30","primary_longitude":"-91.81","state_abbreviation":"LA","state_name":"Louisiana"},{"county_name":"Orleans","description":null,"feat_class":"Populated Place","feature_id":"11370","fips_class":"C5","fips_county_cd":"71","full_county_name":"Orleans Parish","link_title":null,"url":"http:\/\/www.cityofno.com\/","name":"New Orleans","primary_latitude":"29.95","primary_longitude":"-90.07","state_abbreviation":"LA","state_name":"Louisiana"},{"county_name":"Pointe Coupee","description":null,"feat_class":"Populated Place","feature_id":"11371","fips_class":"C1","fips_county_cd":"77","full_county_name":"Pointe Coupee Parish","link_title":null,"url":"http:\/\/www.newroads.net\/","name":"New Roads","primary_latitude":"30.7","primary_longitude":"-91.43","state_abbreviation":"LA","state_name":"Louisiana"},{"county_name":"St. Landry","description":null,"feat_class":"Populated Place","feature_id":"11382","fips_class":"C1","fips_county_cd":"97","full_county_name":"St. Landry Parish","link_title":null,"url":"http:\/\/www.cityofopelousas.com\/","name":"Opelousas","primary_latitude":"30.53","primary_longitude":"-92.08","state_abbreviation":"LA","state_name":"Louisiana"},{"county_name":"Rapides","description":null,"feat_class":"Populated Place","feature_id":"11388","fips_class":"C1","fips_county_cd":"79","full_county_name":"Rapides Parish","link_title":null,"url":"http:\/\/pineville.net\/","name":"Pineville","primary_latitude":"31.32","primary_longitude":"-92.43","state_abbreviation":"LA","state_name":"Louisiana"},{"county_name":"Iberville","description":null,"feat_class":"Populated Place","feature_id":"11391","fips_class":"C1","fips_county_cd":"47","full_county_name":"Iberville Parish","link_title":null,"url":"http:\/\/www.plaquemine.org\/","name":"Plaquemine","primary_latitude":"30.28","primary_longitude":"-91.23","state_abbreviation":"LA","state_name":"Louisiana"},{"county_name":"Tangipahoa","description":null,"feat_class":"Populated Place","feature_id":"11395","fips_class":"C1","fips_county_cd":"105","full_county_name":"Tangipahoa Parish","link_title":null,"url":"http:\/\/www.cityofponchatoula.com\/","name":"Ponchatoula","primary_latitude":"30.43","primary_longitude":"-90.44","state_abbreviation":"LA","state_name":"Louisiana"},{"county_name":"West Baton Rouge","description":null,"feat_class":"Populated Place","feature_id":"11396","fips_class":"C1","fips_county_cd":"121","full_county_name":"West Baton Rouge Parish","link_title":null,"url":"http:\/\/www.portallen.org\/","name":"Port Allen","primary_latitude":"30.45","primary_longitude":"-91.21","state_abbreviation":"LA","state_name":"Louisiana"},{"county_name":"Livingston","description":null,"feat_class":"Populated Place","feature_id":"11398","fips_class":"C1","fips_county_cd":"63","full_county_name":"Livingston Parish","link_title":null,"url":"http:\/\/www.portvincent.govoffice2.com\/","name":"Port Vincent","primary_latitude":"30.33","primary_longitude":"-90.84","state_abbreviation":"LA","state_name":"Louisiana"},{"county_name":"Acadia","description":null,"feat_class":"Populated Place","feature_id":"11402","fips_class":"C1","fips_county_cd":"1","full_county_name":"Acadia Parish","link_title":null,"url":"http:\/\/www.rayne.org\/","name":"Rayne","primary_latitude":"30.23","primary_longitude":"-92.26","state_abbreviation":"LA","state_name":"Louisiana"},{"county_name":"Lincoln","description":null,"feat_class":"Populated Place","feature_id":"11414","fips_class":"C1","fips_county_cd":"61","full_county_name":"Lincoln Parish","link_title":null,"url":"http:\/\/www.ruston.org\/","name":"Ruston","primary_latitude":"32.52","primary_longitude":"-92.63","state_abbreviation":"LA","state_name":"Louisiana"},{"county_name":"West Feliciana","description":null,"feat_class":"Populated Place","feature_id":"11415","fips_class":"C1","fips_county_cd":"125","full_county_name":"West Feliciana Parish","link_title":null,"url":"http:\/\/www.stfrancisville.net\/","name":"Saint Francisville","primary_latitude":"30.77","primary_longitude":"-91.37","state_abbreviation":"LA","state_name":"Louisiana"},{"county_name":"Iberville","description":null,"feat_class":"Populated Place","feature_id":"11416","fips_class":"C1","fips_county_cd":"47","full_county_name":"Iberville Parish","link_title":null,"url":"http:\/\/www.cityofstgabriel.us\/","name":"Saint Gabriel","primary_latitude":"30.25","primary_longitude":"-91.09","state_abbreviation":"LA","state_name":"Louisiana"},{"county_name":"Tensas","description":null,"feat_class":"Populated Place","feature_id":"11417","fips_class":"C1","fips_county_cd":"107","full_county_name":"Tensas Parish","link_title":null,"url":"http:\/\/townofsaintjoseph.com\/","name":"Saint Joseph","primary_latitude":"31.91","primary_longitude":"-91.23","state_abbreviation":"LA","state_name":"Louisiana"},{"county_name":"West Baton Rouge","description":null,"feat_class":"Populated Place","feature_id":"11167","fips_class":"C1","fips_county_cd":"121","full_county_name":"West Baton Rouge Parish","link_title":null,"url":"http:\/\/www.addisla.org\/","name":"Addis","primary_latitude":"30.35","primary_longitude":"-91.26","state_abbreviation":"LA","state_name":"Louisiana"},{"county_name":"Caddo","description":null,"feat_class":"Populated Place","feature_id":"11423","fips_class":"C1","fips_county_cd":"17","full_county_name":"Caddo Parish","link_title":null,"url":"http:\/\/www.ci.shreveport.la.us\/","name":"Shreveport","primary_latitude":"32.52","primary_longitude":"-93.75","state_abbreviation":"LA","state_name":"Louisiana"},{"county_name":"Rapides","description":null,"feat_class":"Populated Place","feature_id":"11169","fips_class":"C1","fips_county_cd":"79","full_county_name":"Rapides Parish","link_title":null,"url":"http:\/\/www.cityofalexandriala.com\/","name":"Alexandria","primary_latitude":"31.31","primary_longitude":"-92.44","state_abbreviation":"LA","state_name":"Louisiana"},{"county_name":"Bienville","description":null,"feat_class":"Populated Place","feature_id":"11173","fips_class":"C1","fips_county_cd":"13","full_county_name":"Bienville Parish","link_title":null,"url":"http:\/\/www.arcadialouisiana.org\/","name":"Arcadia","primary_latitude":"32.54","primary_longitude":"-92.92","state_abbreviation":"LA","state_name":"Louisiana"},{"county_name":"St. Tammany","description":null,"feat_class":"Populated Place","feature_id":"11431","fips_class":"C1","fips_county_cd":"103","full_county_name":"St. Tammany Parish","link_title":null,"url":"http:\/\/www.slidell.la.us\/","name":"Slidell","primary_latitude":"30.27","primary_longitude":"-89.78","state_abbreviation":"LA","state_name":"Louisiana"},{"county_name":"Webster","description":null,"feat_class":"Populated Place","feature_id":"11436","fips_class":"C1","fips_county_cd":"119","full_county_name":"Webster Parish","link_title":null,"url":"http:\/\/www.cityspringhillla.us\/","name":"Springhill","primary_latitude":"33","primary_longitude":"-93.46","state_abbreviation":"LA","state_name":"Louisiana"},{"county_name":"Calcasieu","description":null,"feat_class":"Populated Place","feature_id":"11440","fips_class":"C1","fips_county_cd":"19","full_county_name":"Calcasieu Parish","link_title":null,"url":"http:\/\/www.sulphur.org\/","name":"Sulphur","primary_latitude":"30.23","primary_longitude":"-93.37","state_abbreviation":"LA","state_name":"Louisiana"},{"county_name":"East Baton Rouge","description":null,"feat_class":"Populated Place","feature_id":"11185","fips_class":"C1","fips_county_cd":"33","full_county_name":"East Baton Rouge Parish","link_title":null,"url":"http:\/\/brgov.com\/","name":"Baton Rouge","primary_latitude":"30.45","primary_longitude":"-91.15","state_abbreviation":"LA","state_name":"Louisiana"},{"county_name":"St. Landry","description":null,"feat_class":"Populated Place","feature_id":"11442","fips_class":"C1","fips_county_cd":"97","full_county_name":"St. Landry Parish","link_title":null,"url":"http:\/\/www.sunset.govoffice2.com\/","name":"Sunset","primary_latitude":"30.41","primary_longitude":"-92.06","state_abbreviation":"LA","state_name":"Louisiana"},{"county_name":"Union","description":null,"feat_class":"Populated Place","feature_id":"11188","fips_class":"C1","fips_county_cd":"111","full_county_name":"Union Parish","link_title":null,"url":"http:\/\/www.bernicela.org\/","name":"Bernice","primary_latitude":"32.82","primary_longitude":"-92.65","state_abbreviation":"LA","state_name":"Louisiana"},{"county_name":"St. Mary","description":null,"feat_class":"Populated Place","feature_id":"11189","fips_class":"C1","fips_county_cd":"101","full_county_name":"St. Mary Parish","link_title":null,"url":"http:\/\/www.townofberwick.org\/","name":"Berwick","primary_latitude":"29.69","primary_longitude":"-91.21","state_abbreviation":"LA","state_name":"Louisiana"},{"county_name":"Lafourche","description":null,"feat_class":"Populated Place","feature_id":"11445","fips_class":"C1","fips_county_cd":"57","full_county_name":"Lafourche Parish","link_title":null,"url":"http:\/\/www.ci.thibodaux.la.us\/","name":"Thibodaux","primary_latitude":"29.79","primary_longitude":"-90.82","state_abbreviation":"LA","state_name":"Louisiana"},{"county_name":"Caddo","description":null,"feat_class":"Populated Place","feature_id":"11191","fips_class":"C1","fips_county_cd":"17","full_county_name":"Caddo Parish","link_title":null,"url":"http:\/\/www.townofblanchard.us\/","name":"Blanchard","primary_latitude":"32.58","primary_longitude":"-93.89","state_abbreviation":"LA","state_name":"Louisiana"},{"county_name":"Washington","description":null,"feat_class":"Populated Place","feature_id":"11192","fips_class":"C1","fips_county_cd":"117","full_county_name":"Washington Parish","link_title":null,"url":"http:\/\/www.bogalusa.org\/","name":"Bogalusa","primary_latitude":"30.79","primary_longitude":"-89.84","state_abbreviation":"LA","state_name":"Louisiana"},{"county_name":"Bossier","description":null,"feat_class":"Populated Place","feature_id":"11194","fips_class":"C1","fips_county_cd":"15","full_county_name":"Bossier Parish","link_title":null,"url":"http:\/\/www.bossiercity.org\/","name":"Bossier City","primary_latitude":"32.51","primary_longitude":"-93.73","state_abbreviation":"LA","state_name":"Louisiana"},{"county_name":"Lafayette","description":null,"feat_class":"Populated Place","feature_id":"11197","fips_class":"C1","fips_county_cd":"55","full_county_name":"Lafayette Parish","link_title":null,"url":"http:\/\/www.broussardla.com\/","name":"Broussard","primary_latitude":"30.14","primary_longitude":"-91.96","state_abbreviation":"LA","state_name":"Louisiana"},{"county_name":"Evangeline","description":null,"feat_class":"Populated Place","feature_id":"11453","fips_class":"C1","fips_county_cd":"39","full_county_name":"Evangeline Parish","link_title":null,"url":"http:\/\/www.vpla.com\/","name":"Ville Platte","primary_latitude":"30.68","primary_longitude":"-92.27","state_abbreviation":"LA","state_name":"Louisiana"},{"county_name":"West Baton Rouge","description":null,"feat_class":"Populated Place","feature_id":"11198","fips_class":"C1","fips_county_cd":"121","full_county_name":"West Baton Rouge Parish","link_title":null,"url":"http:\/\/www.bruslyla.com","name":"Brusly","primary_latitude":"30.39","primary_longitude":"-91.25","state_abbreviation":"LA","state_name":"Louisiana"},{"county_name":"Calcasieu","description":null,"feat_class":"Populated Place","feature_id":"11454","fips_class":"C1","fips_county_cd":"19","full_county_name":"Calcasieu Parish","link_title":null,"url":"http:\/\/cityofvinton.com\/","name":"Vinton","primary_latitude":"30.19","primary_longitude":"-93.58","state_abbreviation":"LA","state_name":"Louisiana"},{"county_name":"St. Landry","description":null,"feat_class":"Populated Place","feature_id":"11457","fips_class":"C1","fips_county_cd":"97","full_county_name":"St. Landry Parish","link_title":null,"url":"http:\/\/www.washington-la.org\/","name":"Washington","primary_latitude":"30.61","primary_longitude":"-92.05","state_abbreviation":"LA","state_name":"Louisiana"},{"county_name":"Jefferson Davis","description":null,"feat_class":"Populated Place","feature_id":"11459","fips_class":"C1","fips_county_cd":"53","full_county_name":"Jefferson Davis Parish","link_title":null,"url":"http:\/\/townofwelsh.com\/","name":"Welsh","primary_latitude":"30.23","primary_longitude":"-92.82","state_abbreviation":"LA","state_name":"Louisiana"},{"county_name":"Lafayette","description":null,"feat_class":"Populated Place","feature_id":"11204","fips_class":"C1","fips_county_cd":"55","full_county_name":"Lafayette Parish","link_title":null,"url":"http:\/\/www.carencro.org\/","name":"Carencro","primary_latitude":"30.31","primary_longitude":"-92.04","state_abbreviation":"LA","state_name":"Louisiana"},{"county_name":"Jefferson","description":null,"feat_class":"Populated Place","feature_id":"11462","fips_class":"C1","fips_county_cd":"51","full_county_name":"Jefferson Parish","link_title":null,"url":"http:\/\/www.cityofwestwego.com\/","name":"Westwego","primary_latitude":"29.9","primary_longitude":"-90.14","state_abbreviation":"LA","state_name":"Louisiana"},{"county_name":"Jackson","description":null,"feat_class":"Populated Place","feature_id":"11207","fips_class":"C1","fips_county_cd":"49","full_county_name":"Jackson Parish","link_title":null,"url":"http:\/\/www.townofchatham.org\/","name":"Chatham","primary_latitude":"32.3","primary_longitude":"-92.45","state_abbreviation":"LA","state_name":"Louisiana"},{"county_name":"Lincoln","description":null,"feat_class":"Populated Place","feature_id":"11209","fips_class":"C1","fips_county_cd":"61","full_county_name":"Lincoln Parish","link_title":null,"url":"http:\/\/www.choudrant.org\/","name":"Choudrant","primary_latitude":"32.53","primary_longitude":"-92.51","state_abbreviation":"LA","state_name":"Louisiana"},{"county_name":"Winn","description":null,"feat_class":"Populated Place","feature_id":"11465","fips_class":"C1","fips_county_cd":"127","full_county_name":"Winn Parish","link_title":null,"url":"http:\/\/www.cityofwinnfield.com\/","name":"Winnfield","primary_latitude":"31.92","primary_longitude":"-92.63","state_abbreviation":"LA","state_name":"Louisiana"},{"county_name":"Lafayette","description":null,"feat_class":"Populated Place","feature_id":"11469","fips_class":"C1","fips_county_cd":"55","full_county_name":"Lafayette Parish","link_title":null,"url":"http:\/\/youngsville.us\/","name":"Youngsville","primary_latitude":"30.09","primary_longitude":"-91.99","state_abbreviation":"LA","state_name":"Louisiana"},{"county_name":"Sabine","description":null,"feat_class":"Populated Place","feature_id":"11471","fips_class":"C1","fips_county_cd":"85","full_county_name":"Sabine Parish","link_title":null,"url":"http:\/\/zwollela.net\/","name":"Zwolle","primary_latitude":"31.63","primary_longitude":"-93.64","state_abbreviation":"LA","state_name":"Louisiana"},{"county_name":"St. Tammany","description":null,"feat_class":"Populated Place","feature_id":"11222","fips_class":"C1","fips_county_cd":"103","full_county_name":"St. Tammany Parish","link_title":null,"url":"http:\/\/www.cityofcovingtonla.com\/","name":"Covington","primary_latitude":"30.47","primary_longitude":"-90.1","state_abbreviation":"LA","state_name":"Louisiana"},{"county_name":"Acadia","description":null,"feat_class":"Populated Place","feature_id":"11224","fips_class":"C1","fips_county_cd":"1","full_county_name":"Acadia Parish","link_title":null,"url":"http:\/\/crowley-la.com\/","name":"Crowley","primary_latitude":"30.21","primary_longitude":"-92.37","state_abbreviation":"LA","state_name":"Louisiana"},{"county_name":"St. Landry","description":null,"feat_class":"Populated Place","feature_id":"11250","fips_class":"C1","fips_county_cd":"97","full_county_name":"St. Landry Parish","link_title":null,"url":"http:\/\/www.eunice-la.com\/","name":"Eunice","primary_latitude":"30.49","primary_longitude":"-92.41","state_abbreviation":"LA","state_name":"Louisiana"},{"county_name":"Union","description":null,"feat_class":"Populated Place","feature_id":"11252","fips_class":"C1","fips_county_cd":"111","full_county_name":"Union Parish","link_title":null,"url":"http:\/\/www.farmerville.org\/","name":"Farmerville","primary_latitude":"32.77","primary_longitude":"-92.4","state_abbreviation":"LA","state_name":"Louisiana"},{"county_name":"Concordia","description":null,"feat_class":"Populated Place","feature_id":"11254","fips_class":"C1","fips_county_cd":"29","full_county_name":"Concordia Parish","link_title":null,"url":"http:\/\/www.townofferriday.com\/","name":"Ferriday","primary_latitude":"31.63","primary_longitude":"-91.55","state_abbreviation":"LA","state_name":"Louisiana"},{"county_name":"Washington","description":null,"feat_class":"Populated Place","feature_id":"11262","fips_class":"C1","fips_county_cd":"117","full_county_name":"Washington Parish","link_title":null,"url":"http:\/\/www.townoffranklinton.com\/","name":"Franklinton","primary_latitude":"30.84","primary_longitude":"-90.15","state_abbreviation":"LA","state_name":"Louisiana"},{"county_name":"Livingston","description":null,"feat_class":"Populated Place","feature_id":"11263","fips_class":"C1","fips_county_cd":"63","full_county_name":"Livingston Parish","link_title":null,"url":"http:\/\/frenchsettlement-la.gov\/","name":"French Settlement","primary_latitude":"30.29","primary_longitude":"-90.79","state_abbreviation":"LA","state_name":"Louisiana"}]